{
    "operators": [
        {
            "idx": 0,
            "is_source": true,
            "is_sink": false,
            "name": "op_0",
            "cpu": 10000.0,
            "payload": 0.1879046406614546,
            "weight": 1.0
        },
        {
            "idx": 1,
            "is_source": false,
            "is_sink": false,
            "name": "op_1",
            "cpu": 39558.705729394314,
            "payload": 0.06421025576647643,
            "weight": 1.0
        },
        {
            "idx": 2,
            "is_source": false,
            "is_sink": false,
            "name": "op_2",
            "cpu": 54267.47685121631,
            "payload": 0.14531066883478616,
            "weight": 1.0
        },
        {
            "idx": 3,
            "is_source": false,
            "is_sink": false,
            "name": "op_3",
            "cpu": 49180.689404025376,
            "payload": 0.16922721413684125,
            "weight": 1.0
        },
        {
            "idx": 4,
            "is_source": false,
            "is_sink": false,
            "name": "op_4",
            "cpu": 46303.884271290946,
            "payload": 0.08025300559572128,
            "weight": 1.0
        },
        {
            "idx": 5,
            "is_source": false,
            "is_sink": false,
            "name": "op_5",
            "cpu": 37426.34529496465,
            "payload": 0.05652871067931331,
            "weight": 1.0
        },
        {
            "idx": 6,
            "is_source": false,
            "is_sink": false,
            "name": "op_6",
            "cpu": 32280.383040802317,
            "payload": 0.20264212674395166,
            "weight": 1.0
        },
        {
            "idx": 7,
            "is_source": false,
            "is_sink": false,
            "name": "op_7",
            "cpu": 71801.63581262328,
            "payload": 0.09184674278063518,
            "weight": 1.0
        },
        {
            "idx": 8,
            "is_source": false,
            "is_sink": false,
            "name": "op_8",
            "cpu": 66615.92425641687,
            "payload": 0.022366661187583937,
            "weight": 1.0
        },
        {
            "idx": 9,
            "is_source": false,
            "is_sink": false,
            "name": "op_9",
            "cpu": 17627.578409228478,
            "payload": 0.17571373810418037,
            "weight": 1.0
        },
        {
            "idx": 10,
            "is_source": false,
            "is_sink": false,
            "name": "op_10",
            "cpu": 64937.3769300374,
            "payload": 0.1869157864701813,
            "weight": 1.0
        },
        {
            "idx": 11,
            "is_source": false,
            "is_sink": true,
            "name": "op_11",
            "cpu": 10000.0,
            "payload": 0.0,
            "weight": 1.0
        }
    ],
    "connections": [
        {
            "from_vertex": 0,
            "to_vertex": 1,
            "selectivity": 1.0,
            "weight": 0.1879046406614546
        },
        {
            "from_vertex": 1,
            "to_vertex": 2,
            "selectivity": 1.0,
            "weight": 0.06421025576647643
        },
        {
            "from_vertex": 2,
            "to_vertex": 3,
            "selectivity": 1.0,
            "weight": 0.14531066883478616
        },
        {
            "from_vertex": 3,
            "to_vertex": 4,
            "selectivity": 1.0,
            "weight": 0.16922721413684125
        },
        {
            "from_vertex": 4,
            "to_vertex": 5,
            "selectivity": 1.0,
            "weight": 0.08025300559572128
        },
        {
            "from_vertex": 5,
            "to_vertex": 6,
            "selectivity": 1.0,
            "weight": 0.05652871067931331
        },
        {
            "from_vertex": 6,
            "to_vertex": 7,
            "selectivity": 1.0,
            "weight": 0.20264212674395166
        },
        {
            "from_vertex": 7,
            "to_vertex": 8,
            "selectivity": 1.0,
            "weight": 0.09184674278063518
        },
        {
            "from_vertex": 8,
            "to_vertex": 9,
            "selectivity": 1.0,
            "weight": 0.022366661187583937
        },
        {
            "from_vertex": 9,
            "to_vertex": 10,
            "selectivity": 1.0,
            "weight": 0.17571373810418037
        },
        {
            "from_vertex": 10,
            "to_vertex": 11,
            "selectivity": 1.0,
            "weight": 0.1869157864701813
        }
    ],
    "max_throughput": 10000,
    "event_rate": 10000,
    "num_vms": 2
}