{
    "operators": [
        {
            "idx": 0,
            "is_source": true,
            "is_sink": false,
            "name": "op_0",
            "cpu": 10000.0,
            "payload": 0.11174290802375239,
            "weight": 1.0
        },
        {
            "idx": 1,
            "is_source": false,
            "is_sink": false,
            "name": "op_1",
            "cpu": 45730.58927009392,
            "payload": 0.21792782044793885,
            "weight": 1.0
        },
        {
            "idx": 2,
            "is_source": false,
            "is_sink": false,
            "name": "op_2",
            "cpu": 107760.36604156384,
            "payload": 0.24402948185484039,
            "weight": 1.0
        },
        {
            "idx": 3,
            "is_source": false,
            "is_sink": false,
            "name": "op_3",
            "cpu": 110369.86995447887,
            "payload": 0.21056252993469227,
            "weight": 1.0
        },
        {
            "idx": 4,
            "is_source": false,
            "is_sink": false,
            "name": "op_4",
            "cpu": 37334.925443370616,
            "payload": 0.20242756757088778,
            "weight": 1.0
        },
        {
            "idx": 5,
            "is_source": false,
            "is_sink": false,
            "name": "op_5",
            "cpu": 62049.58168011316,
            "payload": 0.0063323639696175145,
            "weight": 1.0
        },
        {
            "idx": 6,
            "is_source": false,
            "is_sink": false,
            "name": "op_6",
            "cpu": 81329.12493637655,
            "payload": 0.09259129799877054,
            "weight": 1.0
        },
        {
            "idx": 7,
            "is_source": false,
            "is_sink": false,
            "name": "op_7",
            "cpu": 35425.54267400306,
            "payload": 0.21562556392612944,
            "weight": 1.0
        },
        {
            "idx": 8,
            "is_source": false,
            "is_sink": true,
            "name": "op_8",
            "cpu": 10000.0,
            "payload": 0.0,
            "weight": 1.0
        }
    ],
    "connections": [
        {
            "from_vertex": 0,
            "to_vertex": 1,
            "selectivity": 1.0,
            "weight": 0.11174290802375239
        },
        {
            "from_vertex": 1,
            "to_vertex": 2,
            "selectivity": 1.0,
            "weight": 0.21792782044793885
        },
        {
            "from_vertex": 2,
            "to_vertex": 3,
            "selectivity": 1.0,
            "weight": 0.24402948185484039
        },
        {
            "from_vertex": 3,
            "to_vertex": 4,
            "selectivity": 1.0,
            "weight": 0.21056252993469227
        },
        {
            "from_vertex": 4,
            "to_vertex": 5,
            "selectivity": 1.0,
            "weight": 0.20242756757088778
        },
        {
            "from_vertex": 5,
            "to_vertex": 6,
            "selectivity": 1.0,
            "weight": 0.0063323639696175145
        },
        {
            "from_vertex": 6,
            "to_vertex": 7,
            "selectivity": 1.0,
            "weight": 0.09259129799877054
        },
        {
            "from_vertex": 7,
            "to_vertex": 8,
            "selectivity": 1.0,
            "weight": 0.21562556392612944
        }
    ],
    "max_throughput": 10000,
    "event_rate": 10000,
    "num_vms": 2
}