{
    "operators": [
        {
            "idx": 0,
            "is_source": true,
            "is_sink": false,
            "name": "op_0",
            "cpu": 10000.0,
            "payload": 0.3591322654688746,
            "weight": 1.0,
            "weighted_cpu": 10000.0
        },
        {
            "idx": 1,
            "is_source": false,
            "is_sink": false,
            "name": "op_1",
            "cpu": 93339.0377971535,
            "payload": 0.0060398130355081014,
            "weight": 0.2,
            "weighted_cpu": 18667.8075594307
        },
        {
            "idx": 2,
            "is_source": false,
            "is_sink": false,
            "name": "op_2",
            "cpu": 93339.0377971535,
            "payload": 0.09476542147075379,
            "weight": 0.2,
            "weighted_cpu": 18667.8075594307
        },
        {
            "idx": 3,
            "is_source": false,
            "is_sink": false,
            "name": "op_3",
            "cpu": 93339.0377971535,
            "payload": 0.22994692853194026,
            "weight": 0.2,
            "weighted_cpu": 18667.8075594307
        },
        {
            "idx": 4,
            "is_source": false,
            "is_sink": false,
            "name": "op_4",
            "cpu": 93339.0377971535,
            "payload": 0.14115635552831018,
            "weight": 0.2,
            "weighted_cpu": 18667.8075594307
        },
        {
            "idx": 5,
            "is_source": false,
            "is_sink": false,
            "name": "op_5",
            "cpu": 93339.0377971535,
            "payload": 0.19648924930725464,
            "weight": 0.2,
            "weighted_cpu": 18667.8075594307
        },
        {
            "idx": 6,
            "is_source": false,
            "is_sink": false,
            "name": "op_6",
            "cpu": 109350.84062081897,
            "payload": 0.2562414582136154,
            "weight": 0.2,
            "weighted_cpu": 21870.168124163796
        },
        {
            "idx": 7,
            "is_source": false,
            "is_sink": false,
            "name": "op_7",
            "cpu": 109350.84062081897,
            "payload": 0.008501160193407187,
            "weight": 0.2,
            "weighted_cpu": 21870.168124163796
        },
        {
            "idx": 8,
            "is_source": false,
            "is_sink": false,
            "name": "op_8",
            "cpu": 109350.84062081897,
            "payload": 0.1408102980760076,
            "weight": 0.2,
            "weighted_cpu": 21870.168124163796
        },
        {
            "idx": 9,
            "is_source": false,
            "is_sink": false,
            "name": "op_9",
            "cpu": 109350.84062081897,
            "payload": 0.312503555802867,
            "weight": 0.2,
            "weighted_cpu": 21870.168124163796
        },
        {
            "idx": 10,
            "is_source": false,
            "is_sink": false,
            "name": "op_10",
            "cpu": 109350.84062081897,
            "payload": 0.24134135242785631,
            "weight": 0.2,
            "weighted_cpu": 21870.168124163796
        },
        {
            "idx": 11,
            "is_source": false,
            "is_sink": false,
            "name": "op_11",
            "cpu": 226933.59827555847,
            "payload": 0.06584095268366341,
            "weight": 0.2,
            "weighted_cpu": 45386.719655111694
        },
        {
            "idx": 12,
            "is_source": false,
            "is_sink": false,
            "name": "op_12",
            "cpu": 226933.59827555847,
            "payload": 0.3867699758043632,
            "weight": 0.2,
            "weighted_cpu": 45386.719655111694
        },
        {
            "idx": 13,
            "is_source": false,
            "is_sink": false,
            "name": "op_13",
            "cpu": 226933.59827555847,
            "payload": 0.176525407818384,
            "weight": 0.2,
            "weighted_cpu": 45386.719655111694
        },
        {
            "idx": 14,
            "is_source": false,
            "is_sink": false,
            "name": "op_14",
            "cpu": 226933.59827555847,
            "payload": 0.03509167128239049,
            "weight": 0.2,
            "weighted_cpu": 45386.719655111694
        },
        {
            "idx": 15,
            "is_source": false,
            "is_sink": false,
            "name": "op_15",
            "cpu": 226933.59827555847,
            "payload": 0.4624152396636565,
            "weight": 0.2,
            "weighted_cpu": 45386.719655111694
        },
        {
            "idx": 16,
            "is_source": false,
            "is_sink": false,
            "name": "op_16",
            "cpu": 550376.523306469,
            "payload": 0.0958077850678195,
            "weight": 0.2,
            "weighted_cpu": 110075.3046612938
        },
        {
            "idx": 17,
            "is_source": false,
            "is_sink": false,
            "name": "op_17",
            "cpu": 550376.523306469,
            "payload": 0.20441512350657437,
            "weight": 0.2,
            "weighted_cpu": 110075.3046612938
        },
        {
            "idx": 18,
            "is_source": false,
            "is_sink": false,
            "name": "op_18",
            "cpu": 550376.523306469,
            "payload": 0.38719373234733906,
            "weight": 0.2,
            "weighted_cpu": 110075.3046612938
        },
        {
            "idx": 19,
            "is_source": false,
            "is_sink": false,
            "name": "op_19",
            "cpu": 550376.523306469,
            "payload": 0.16682631532441056,
            "weight": 0.2,
            "weighted_cpu": 110075.3046612938
        },
        {
            "idx": 20,
            "is_source": false,
            "is_sink": false,
            "name": "op_20",
            "cpu": 550376.523306469,
            "payload": 0.1496605062875429,
            "weight": 0.2,
            "weighted_cpu": 110075.3046612938
        },
        {
            "idx": 21,
            "is_source": false,
            "is_sink": true,
            "name": "op_21",
            "cpu": 10000.0,
            "payload": 0.0,
            "weight": 1.0,
            "weighted_cpu": 10000.0
        }
    ],
    "connections": [
        {
            "from_vertex": 0,
            "to_vertex": 1,
            "selectivity": 0.2,
            "weight": 0.07182645309377493
        },
        {
            "from_vertex": 0,
            "to_vertex": 2,
            "selectivity": 0.2,
            "weight": 0.07182645309377493
        },
        {
            "from_vertex": 0,
            "to_vertex": 3,
            "selectivity": 0.2,
            "weight": 0.07182645309377493
        },
        {
            "from_vertex": 0,
            "to_vertex": 4,
            "selectivity": 0.2,
            "weight": 0.07182645309377493
        },
        {
            "from_vertex": 0,
            "to_vertex": 5,
            "selectivity": 0.2,
            "weight": 0.07182645309377493
        },
        {
            "from_vertex": 1,
            "to_vertex": 6,
            "selectivity": 1.0,
            "weight": 0.0012079626071016204
        },
        {
            "from_vertex": 2,
            "to_vertex": 7,
            "selectivity": 1.0,
            "weight": 0.018953084294150758
        },
        {
            "from_vertex": 3,
            "to_vertex": 8,
            "selectivity": 1.0,
            "weight": 0.04598938570638805
        },
        {
            "from_vertex": 4,
            "to_vertex": 9,
            "selectivity": 1.0,
            "weight": 0.028231271105662037
        },
        {
            "from_vertex": 5,
            "to_vertex": 10,
            "selectivity": 1.0,
            "weight": 0.039297849861450934
        },
        {
            "from_vertex": 6,
            "to_vertex": 11,
            "selectivity": 1.0,
            "weight": 0.05124829164272308
        },
        {
            "from_vertex": 7,
            "to_vertex": 12,
            "selectivity": 1.0,
            "weight": 0.0017002320386814375
        },
        {
            "from_vertex": 8,
            "to_vertex": 13,
            "selectivity": 1.0,
            "weight": 0.028162059615201518
        },
        {
            "from_vertex": 9,
            "to_vertex": 14,
            "selectivity": 1.0,
            "weight": 0.0625007111605734
        },
        {
            "from_vertex": 10,
            "to_vertex": 15,
            "selectivity": 1.0,
            "weight": 0.048268270485571266
        },
        {
            "from_vertex": 11,
            "to_vertex": 16,
            "selectivity": 1.0,
            "weight": 0.013168190536732682
        },
        {
            "from_vertex": 12,
            "to_vertex": 17,
            "selectivity": 1.0,
            "weight": 0.07735399516087264
        },
        {
            "from_vertex": 13,
            "to_vertex": 18,
            "selectivity": 1.0,
            "weight": 0.0353050815636768
        },
        {
            "from_vertex": 14,
            "to_vertex": 19,
            "selectivity": 1.0,
            "weight": 0.0070183342564780985
        },
        {
            "from_vertex": 15,
            "to_vertex": 20,
            "selectivity": 1.0,
            "weight": 0.09248304793273131
        },
        {
            "from_vertex": 16,
            "to_vertex": 21,
            "selectivity": 1.0,
            "weight": 0.019161557013563903
        },
        {
            "from_vertex": 17,
            "to_vertex": 21,
            "selectivity": 1.0,
            "weight": 0.04088302470131488
        },
        {
            "from_vertex": 18,
            "to_vertex": 21,
            "selectivity": 1.0,
            "weight": 0.07743874646946781
        },
        {
            "from_vertex": 19,
            "to_vertex": 21,
            "selectivity": 1.0,
            "weight": 0.03336526306488211
        },
        {
            "from_vertex": 20,
            "to_vertex": 21,
            "selectivity": 1.0,
            "weight": 0.029932101257508583
        }
    ],
    "max_throughput": 10000,
    "event_rate": 10000,
    "num_vms": 4
}