{
    "operators": [
        {
            "idx": 0,
            "is_source": true,
            "is_sink": false,
            "name": "op_0",
            "cpu": 10000.0,
            "payload": 0.324902480698523,
            "weight": 1.0,
            "weighted_cpu": 10000.0
        },
        {
            "idx": 1,
            "is_source": false,
            "is_sink": false,
            "name": "op_1",
            "cpu": 344412.93766857026,
            "payload": 0.03046859627572529,
            "weight": 0.08333333333333333,
            "weighted_cpu": 28701.07813904752
        },
        {
            "idx": 2,
            "is_source": false,
            "is_sink": false,
            "name": "op_2",
            "cpu": 344412.93766857026,
            "payload": 0.20585009283628541,
            "weight": 0.08333333333333333,
            "weighted_cpu": 28701.07813904752
        },
        {
            "idx": 3,
            "is_source": false,
            "is_sink": false,
            "name": "op_3",
            "cpu": 344412.93766857026,
            "payload": 0.21360943218779543,
            "weight": 0.08333333333333333,
            "weighted_cpu": 28701.07813904752
        },
        {
            "idx": 4,
            "is_source": false,
            "is_sink": false,
            "name": "op_4",
            "cpu": 344412.93766857026,
            "payload": 0.14507442273279186,
            "weight": 0.08333333333333333,
            "weighted_cpu": 28701.07813904752
        },
        {
            "idx": 5,
            "is_source": false,
            "is_sink": false,
            "name": "op_5",
            "cpu": 344412.93766857026,
            "payload": 0.05798829858197918,
            "weight": 0.08333333333333333,
            "weighted_cpu": 28701.07813904752
        },
        {
            "idx": 6,
            "is_source": false,
            "is_sink": false,
            "name": "op_6",
            "cpu": 344412.93766857026,
            "payload": 0.022217233087799604,
            "weight": 0.08333333333333333,
            "weighted_cpu": 28701.07813904752
        },
        {
            "idx": 7,
            "is_source": false,
            "is_sink": false,
            "name": "op_7",
            "cpu": 344412.93766857026,
            "payload": 0.09755569833162392,
            "weight": 0.08333333333333333,
            "weighted_cpu": 28701.07813904752
        },
        {
            "idx": 8,
            "is_source": false,
            "is_sink": false,
            "name": "op_8",
            "cpu": 344412.93766857026,
            "payload": 0.11813555037017914,
            "weight": 0.08333333333333333,
            "weighted_cpu": 28701.07813904752
        },
        {
            "idx": 9,
            "is_source": false,
            "is_sink": false,
            "name": "op_9",
            "cpu": 344412.93766857026,
            "payload": 0.14015571866735105,
            "weight": 0.08333333333333333,
            "weighted_cpu": 28701.07813904752
        },
        {
            "idx": 10,
            "is_source": false,
            "is_sink": false,
            "name": "op_10",
            "cpu": 344412.93766857026,
            "payload": 0.37162497480531503,
            "weight": 0.08333333333333333,
            "weighted_cpu": 28701.07813904752
        },
        {
            "idx": 11,
            "is_source": false,
            "is_sink": false,
            "name": "op_11",
            "cpu": 344412.93766857026,
            "payload": 0.22065663161768878,
            "weight": 0.08333333333333333,
            "weighted_cpu": 28701.07813904752
        },
        {
            "idx": 12,
            "is_source": false,
            "is_sink": false,
            "name": "op_12",
            "cpu": 344412.93766857026,
            "payload": 0.13422105842418564,
            "weight": 0.08333333333333333,
            "weighted_cpu": 28701.07813904752
        },
        {
            "idx": 13,
            "is_source": false,
            "is_sink": false,
            "name": "op_13",
            "cpu": 885587.0623314297,
            "payload": 0.26968863724681624,
            "weight": 0.08333333333333333,
            "weighted_cpu": 73798.92186095247
        },
        {
            "idx": 14,
            "is_source": false,
            "is_sink": false,
            "name": "op_14",
            "cpu": 885587.0623314297,
            "payload": 0.15546277488880866,
            "weight": 0.08333333333333333,
            "weighted_cpu": 73798.92186095247
        },
        {
            "idx": 15,
            "is_source": false,
            "is_sink": false,
            "name": "op_15",
            "cpu": 885587.0623314297,
            "payload": 0.09397053013264473,
            "weight": 0.08333333333333333,
            "weighted_cpu": 73798.92186095247
        },
        {
            "idx": 16,
            "is_source": false,
            "is_sink": false,
            "name": "op_16",
            "cpu": 885587.0623314297,
            "payload": 0.12870980737622562,
            "weight": 0.08333333333333333,
            "weighted_cpu": 73798.92186095247
        },
        {
            "idx": 17,
            "is_source": false,
            "is_sink": false,
            "name": "op_17",
            "cpu": 885587.0623314297,
            "payload": 0.19038990508374176,
            "weight": 0.08333333333333333,
            "weighted_cpu": 73798.92186095247
        },
        {
            "idx": 18,
            "is_source": false,
            "is_sink": false,
            "name": "op_18",
            "cpu": 885587.0623314297,
            "payload": 0.4474315634642257,
            "weight": 0.08333333333333333,
            "weighted_cpu": 73798.92186095247
        },
        {
            "idx": 19,
            "is_source": false,
            "is_sink": false,
            "name": "op_19",
            "cpu": 885587.0623314297,
            "payload": 0.0056440645679348145,
            "weight": 0.08333333333333333,
            "weighted_cpu": 73798.92186095247
        },
        {
            "idx": 20,
            "is_source": false,
            "is_sink": false,
            "name": "op_20",
            "cpu": 885587.0623314297,
            "payload": 0.2534067920336067,
            "weight": 0.08333333333333333,
            "weighted_cpu": 73798.92186095247
        },
        {
            "idx": 21,
            "is_source": false,
            "is_sink": false,
            "name": "op_21",
            "cpu": 885587.0623314297,
            "payload": 0.4361823549710169,
            "weight": 0.08333333333333333,
            "weighted_cpu": 73798.92186095247
        },
        {
            "idx": 22,
            "is_source": false,
            "is_sink": false,
            "name": "op_22",
            "cpu": 885587.0623314297,
            "payload": 0.44848470157417214,
            "weight": 0.08333333333333333,
            "weighted_cpu": 73798.92186095247
        },
        {
            "idx": 23,
            "is_source": false,
            "is_sink": false,
            "name": "op_23",
            "cpu": 885587.0623314297,
            "payload": 0.19219544566905444,
            "weight": 0.08333333333333333,
            "weighted_cpu": 73798.92186095247
        },
        {
            "idx": 24,
            "is_source": false,
            "is_sink": false,
            "name": "op_24",
            "cpu": 885587.0623314297,
            "payload": 0.4854983299333044,
            "weight": 0.08333333333333333,
            "weighted_cpu": 73798.92186095247
        },
        {
            "idx": 25,
            "is_source": false,
            "is_sink": true,
            "name": "op_25",
            "cpu": 10000.0,
            "payload": 0.0,
            "weight": 1.0,
            "weighted_cpu": 10000.0
        }
    ],
    "connections": [
        {
            "from_vertex": 0,
            "to_vertex": 1,
            "selectivity": 0.08333333333333333,
            "weight": 0.027075206724876916
        },
        {
            "from_vertex": 0,
            "to_vertex": 2,
            "selectivity": 0.08333333333333333,
            "weight": 0.027075206724876916
        },
        {
            "from_vertex": 0,
            "to_vertex": 3,
            "selectivity": 0.08333333333333333,
            "weight": 0.027075206724876916
        },
        {
            "from_vertex": 0,
            "to_vertex": 4,
            "selectivity": 0.08333333333333333,
            "weight": 0.027075206724876916
        },
        {
            "from_vertex": 0,
            "to_vertex": 5,
            "selectivity": 0.08333333333333333,
            "weight": 0.027075206724876916
        },
        {
            "from_vertex": 0,
            "to_vertex": 6,
            "selectivity": 0.08333333333333333,
            "weight": 0.027075206724876916
        },
        {
            "from_vertex": 0,
            "to_vertex": 7,
            "selectivity": 0.08333333333333333,
            "weight": 0.027075206724876916
        },
        {
            "from_vertex": 0,
            "to_vertex": 8,
            "selectivity": 0.08333333333333333,
            "weight": 0.027075206724876916
        },
        {
            "from_vertex": 0,
            "to_vertex": 9,
            "selectivity": 0.08333333333333333,
            "weight": 0.027075206724876916
        },
        {
            "from_vertex": 0,
            "to_vertex": 10,
            "selectivity": 0.08333333333333333,
            "weight": 0.027075206724876916
        },
        {
            "from_vertex": 0,
            "to_vertex": 11,
            "selectivity": 0.08333333333333333,
            "weight": 0.027075206724876916
        },
        {
            "from_vertex": 0,
            "to_vertex": 12,
            "selectivity": 0.08333333333333333,
            "weight": 0.027075206724876916
        },
        {
            "from_vertex": 1,
            "to_vertex": 13,
            "selectivity": 1.0,
            "weight": 0.002539049689643774
        },
        {
            "from_vertex": 2,
            "to_vertex": 14,
            "selectivity": 1.0,
            "weight": 0.017154174403023782
        },
        {
            "from_vertex": 3,
            "to_vertex": 15,
            "selectivity": 1.0,
            "weight": 0.01780078601564962
        },
        {
            "from_vertex": 4,
            "to_vertex": 16,
            "selectivity": 1.0,
            "weight": 0.012089535227732654
        },
        {
            "from_vertex": 5,
            "to_vertex": 17,
            "selectivity": 1.0,
            "weight": 0.004832358215164931
        },
        {
            "from_vertex": 6,
            "to_vertex": 18,
            "selectivity": 1.0,
            "weight": 0.0018514360906499668
        },
        {
            "from_vertex": 7,
            "to_vertex": 19,
            "selectivity": 1.0,
            "weight": 0.008129641527635326
        },
        {
            "from_vertex": 8,
            "to_vertex": 20,
            "selectivity": 1.0,
            "weight": 0.009844629197514929
        },
        {
            "from_vertex": 9,
            "to_vertex": 21,
            "selectivity": 1.0,
            "weight": 0.011679643222279254
        },
        {
            "from_vertex": 10,
            "to_vertex": 22,
            "selectivity": 1.0,
            "weight": 0.03096874790044292
        },
        {
            "from_vertex": 11,
            "to_vertex": 23,
            "selectivity": 1.0,
            "weight": 0.018388052634807396
        },
        {
            "from_vertex": 12,
            "to_vertex": 24,
            "selectivity": 1.0,
            "weight": 0.01118508820201547
        },
        {
            "from_vertex": 13,
            "to_vertex": 25,
            "selectivity": 1.0,
            "weight": 0.022474053103901354
        },
        {
            "from_vertex": 14,
            "to_vertex": 25,
            "selectivity": 1.0,
            "weight": 0.012955231240734055
        },
        {
            "from_vertex": 15,
            "to_vertex": 25,
            "selectivity": 1.0,
            "weight": 0.007830877511053727
        },
        {
            "from_vertex": 16,
            "to_vertex": 25,
            "selectivity": 1.0,
            "weight": 0.010725817281352135
        },
        {
            "from_vertex": 17,
            "to_vertex": 25,
            "selectivity": 1.0,
            "weight": 0.015865825423645147
        },
        {
            "from_vertex": 18,
            "to_vertex": 25,
            "selectivity": 1.0,
            "weight": 0.0372859636220188
        },
        {
            "from_vertex": 19,
            "to_vertex": 25,
            "selectivity": 1.0,
            "weight": 0.00047033871399456784
        },
        {
            "from_vertex": 20,
            "to_vertex": 25,
            "selectivity": 1.0,
            "weight": 0.021117232669467224
        },
        {
            "from_vertex": 21,
            "to_vertex": 25,
            "selectivity": 1.0,
            "weight": 0.03634852958091807
        },
        {
            "from_vertex": 22,
            "to_vertex": 25,
            "selectivity": 1.0,
            "weight": 0.03737372513118101
        },
        {
            "from_vertex": 23,
            "to_vertex": 25,
            "selectivity": 1.0,
            "weight": 0.01601628713908787
        },
        {
            "from_vertex": 24,
            "to_vertex": 25,
            "selectivity": 1.0,
            "weight": 0.0404581941611087
        }
    ],
    "max_throughput": 10000,
    "event_rate": 10000,
    "num_vms": 5
}