{
    "operators": [
        {
            "idx": 0,
            "is_source": true,
            "is_sink": false,
            "name": "op_0",
            "cpu": 10000.0,
            "payload": 0.07046408216589359,
            "weight": 1.0
        },
        {
            "idx": 1,
            "is_source": false,
            "is_sink": false,
            "name": "op_1",
            "cpu": 267405.3773427936,
            "payload": 0.058044100950025115,
            "weight": 0.5
        },
        {
            "idx": 2,
            "is_source": false,
            "is_sink": false,
            "name": "op_2",
            "cpu": 267405.3773427936,
            "payload": 0.027604918636306427,
            "weight": 0.5
        },
        {
            "idx": 3,
            "is_source": false,
            "is_sink": false,
            "name": "op_3",
            "cpu": 212594.62265720638,
            "payload": 0.07563340992691181,
            "weight": 0.5
        },
        {
            "idx": 4,
            "is_source": false,
            "is_sink": false,
            "name": "op_4",
            "cpu": 212594.62265720638,
            "payload": 0.02605870317176154,
            "weight": 0.5
        },
        {
            "idx": 5,
            "is_source": false,
            "is_sink": true,
            "name": "op_5",
            "cpu": 10000.0,
            "payload": 0.0,
            "weight": 1.0
        }
    ],
    "connections": [
        {
            "from_vertex": 0,
            "to_vertex": 1,
            "selectivity": 0.5,
            "weight": 0.035232041082946794
        },
        {
            "from_vertex": 0,
            "to_vertex": 2,
            "selectivity": 0.5,
            "weight": 0.035232041082946794
        },
        {
            "from_vertex": 1,
            "to_vertex": 3,
            "selectivity": 1.0,
            "weight": 0.029022050475012558
        },
        {
            "from_vertex": 2,
            "to_vertex": 4,
            "selectivity": 1.0,
            "weight": 0.013802459318153213
        },
        {
            "from_vertex": 3,
            "to_vertex": 5,
            "selectivity": 1.0,
            "weight": 0.037816704963455905
        },
        {
            "from_vertex": 4,
            "to_vertex": 5,
            "selectivity": 1.0,
            "weight": 0.01302935158588077
        }
    ],
    "max_throughput": 10000,
    "event_rate": 10000,
    "num_vms": 2
}