{
    "operators": [
        {
            "idx": 0,
            "is_source": true,
            "is_sink": false,
            "name": "op_0",
            "cpu": 10000.0,
            "payload": 0.3752851274497687,
            "weight": 1.0,
            "weighted_cpu": 10000.0
        },
        {
            "idx": 1,
            "is_source": false,
            "is_sink": false,
            "name": "op_1",
            "cpu": 72529.98407541522,
            "payload": 0.23945849010489434,
            "weight": 0.5,
            "weighted_cpu": 36264.99203770761
        },
        {
            "idx": 2,
            "is_source": false,
            "is_sink": false,
            "name": "op_2",
            "cpu": 72529.98407541522,
            "payload": 0.14497954505745908,
            "weight": 0.5,
            "weighted_cpu": 36264.99203770761
        },
        {
            "idx": 3,
            "is_source": false,
            "is_sink": false,
            "name": "op_3",
            "cpu": 207228.58520584987,
            "payload": 0.31055881213223085,
            "weight": 0.5,
            "weighted_cpu": 103614.29260292494
        },
        {
            "idx": 4,
            "is_source": false,
            "is_sink": false,
            "name": "op_4",
            "cpu": 207228.58520584987,
            "payload": 0.4209454853505467,
            "weight": 0.5,
            "weighted_cpu": 103614.29260292494
        },
        {
            "idx": 5,
            "is_source": false,
            "is_sink": false,
            "name": "op_5",
            "cpu": 153565.51943353037,
            "payload": 0.48599398639369024,
            "weight": 0.5,
            "weighted_cpu": 76782.75971676518
        },
        {
            "idx": 6,
            "is_source": false,
            "is_sink": false,
            "name": "op_6",
            "cpu": 153565.51943353037,
            "payload": 0.26565158241298487,
            "weight": 0.5,
            "weighted_cpu": 76782.75971676518
        },
        {
            "idx": 7,
            "is_source": false,
            "is_sink": false,
            "name": "op_7",
            "cpu": 15300.60690126913,
            "payload": 0.062435760503188664,
            "weight": 0.5,
            "weighted_cpu": 7650.303450634565
        },
        {
            "idx": 8,
            "is_source": false,
            "is_sink": false,
            "name": "op_8",
            "cpu": 15300.60690126913,
            "payload": 0.38075044494187943,
            "weight": 0.5,
            "weighted_cpu": 7650.303450634565
        },
        {
            "idx": 9,
            "is_source": false,
            "is_sink": false,
            "name": "op_9",
            "cpu": 76834.14359808182,
            "payload": 0.25667443623971004,
            "weight": 0.5,
            "weighted_cpu": 38417.07179904091
        },
        {
            "idx": 10,
            "is_source": false,
            "is_sink": false,
            "name": "op_10",
            "cpu": 76834.14359808182,
            "payload": 0.26342916589301535,
            "weight": 0.5,
            "weighted_cpu": 38417.07179904091
        },
        {
            "idx": 11,
            "is_source": false,
            "is_sink": false,
            "name": "op_11",
            "cpu": 149906.48672045558,
            "payload": 0.33317240939581044,
            "weight": 0.5,
            "weighted_cpu": 74953.24336022779
        },
        {
            "idx": 12,
            "is_source": false,
            "is_sink": false,
            "name": "op_12",
            "cpu": 149906.48672045558,
            "payload": 0.45141388071104527,
            "weight": 0.5,
            "weighted_cpu": 74953.24336022779
        },
        {
            "idx": 13,
            "is_source": false,
            "is_sink": false,
            "name": "op_13",
            "cpu": 74608.74411480564,
            "payload": 0.4596726996703047,
            "weight": 0.5,
            "weighted_cpu": 37304.37205740282
        },
        {
            "idx": 14,
            "is_source": false,
            "is_sink": false,
            "name": "op_14",
            "cpu": 74608.74411480564,
            "payload": 0.08684855700994965,
            "weight": 0.5,
            "weighted_cpu": 37304.37205740282
        },
        {
            "idx": 15,
            "is_source": false,
            "is_sink": false,
            "name": "op_15",
            "cpu": 43342.109501214014,
            "payload": 0.37759682282822477,
            "weight": 0.5,
            "weighted_cpu": 21671.054750607007
        },
        {
            "idx": 16,
            "is_source": false,
            "is_sink": false,
            "name": "op_16",
            "cpu": 43342.109501214014,
            "payload": 0.32540162213837404,
            "weight": 0.5,
            "weighted_cpu": 21671.054750607007
        },
        {
            "idx": 17,
            "is_source": false,
            "is_sink": false,
            "name": "op_17",
            "cpu": 127862.98897492474,
            "payload": 0.28083121575677633,
            "weight": 0.5,
            "weighted_cpu": 63931.49448746237
        },
        {
            "idx": 18,
            "is_source": false,
            "is_sink": false,
            "name": "op_18",
            "cpu": 127862.98897492474,
            "payload": 0.06491518733472262,
            "weight": 0.5,
            "weighted_cpu": 63931.49448746237
        },
        {
            "idx": 19,
            "is_source": false,
            "is_sink": false,
            "name": "op_19",
            "cpu": 58820.83147445349,
            "payload": 0.0023515314142881216,
            "weight": 0.5,
            "weighted_cpu": 29410.415737226744
        },
        {
            "idx": 20,
            "is_source": false,
            "is_sink": false,
            "name": "op_20",
            "cpu": 58820.83147445349,
            "payload": 0.09260584602195149,
            "weight": 0.5,
            "weighted_cpu": 29410.415737226744
        },
        {
            "idx": 21,
            "is_source": false,
            "is_sink": true,
            "name": "op_21",
            "cpu": 10000.0,
            "payload": 0.0,
            "weight": 1.0,
            "weighted_cpu": 10000.0
        }
    ],
    "connections": [
        {
            "from_vertex": 0,
            "to_vertex": 1,
            "selectivity": 0.5,
            "weight": 0.18764256372488436
        },
        {
            "from_vertex": 0,
            "to_vertex": 2,
            "selectivity": 0.5,
            "weight": 0.18764256372488436
        },
        {
            "from_vertex": 1,
            "to_vertex": 3,
            "selectivity": 1.0,
            "weight": 0.11972924505244717
        },
        {
            "from_vertex": 2,
            "to_vertex": 4,
            "selectivity": 1.0,
            "weight": 0.07248977252872954
        },
        {
            "from_vertex": 3,
            "to_vertex": 5,
            "selectivity": 1.0,
            "weight": 0.15527940606611543
        },
        {
            "from_vertex": 4,
            "to_vertex": 6,
            "selectivity": 1.0,
            "weight": 0.21047274267527336
        },
        {
            "from_vertex": 5,
            "to_vertex": 7,
            "selectivity": 1.0,
            "weight": 0.24299699319684512
        },
        {
            "from_vertex": 6,
            "to_vertex": 8,
            "selectivity": 1.0,
            "weight": 0.13282579120649243
        },
        {
            "from_vertex": 7,
            "to_vertex": 9,
            "selectivity": 1.0,
            "weight": 0.031217880251594332
        },
        {
            "from_vertex": 8,
            "to_vertex": 10,
            "selectivity": 1.0,
            "weight": 0.19037522247093971
        },
        {
            "from_vertex": 9,
            "to_vertex": 11,
            "selectivity": 1.0,
            "weight": 0.12833721811985502
        },
        {
            "from_vertex": 10,
            "to_vertex": 12,
            "selectivity": 1.0,
            "weight": 0.13171458294650767
        },
        {
            "from_vertex": 11,
            "to_vertex": 13,
            "selectivity": 1.0,
            "weight": 0.16658620469790522
        },
        {
            "from_vertex": 12,
            "to_vertex": 14,
            "selectivity": 1.0,
            "weight": 0.22570694035552263
        },
        {
            "from_vertex": 13,
            "to_vertex": 15,
            "selectivity": 1.0,
            "weight": 0.22983634983515236
        },
        {
            "from_vertex": 14,
            "to_vertex": 16,
            "selectivity": 1.0,
            "weight": 0.04342427850497482
        },
        {
            "from_vertex": 15,
            "to_vertex": 17,
            "selectivity": 1.0,
            "weight": 0.18879841141411238
        },
        {
            "from_vertex": 16,
            "to_vertex": 18,
            "selectivity": 1.0,
            "weight": 0.16270081106918702
        },
        {
            "from_vertex": 17,
            "to_vertex": 19,
            "selectivity": 1.0,
            "weight": 0.14041560787838817
        },
        {
            "from_vertex": 18,
            "to_vertex": 20,
            "selectivity": 1.0,
            "weight": 0.03245759366736131
        },
        {
            "from_vertex": 19,
            "to_vertex": 21,
            "selectivity": 1.0,
            "weight": 0.0011757657071440608
        },
        {
            "from_vertex": 20,
            "to_vertex": 21,
            "selectivity": 1.0,
            "weight": 0.046302923010975744
        }
    ],
    "max_throughput": 10000,
    "event_rate": 10000,
    "num_vms": 4
}