{
    "operators": [
        {
            "idx": 0,
            "is_source": true,
            "is_sink": false,
            "name": "op_0",
            "cpu": 10000.0,
            "payload": 0.4049373618134404,
            "weight": 1.0,
            "weighted_cpu": 10000.0
        },
        {
            "idx": 1,
            "is_source": false,
            "is_sink": false,
            "name": "op_1",
            "cpu": 334034.1725139262,
            "payload": 0.3799385939313563,
            "weight": 0.14285714285714285,
            "weighted_cpu": 47719.16750198946
        },
        {
            "idx": 2,
            "is_source": false,
            "is_sink": false,
            "name": "op_2",
            "cpu": 334034.1725139262,
            "payload": 0.051948460519802064,
            "weight": 0.14285714285714285,
            "weighted_cpu": 47719.16750198946
        },
        {
            "idx": 3,
            "is_source": false,
            "is_sink": false,
            "name": "op_3",
            "cpu": 334034.1725139262,
            "payload": 0.23144159431035305,
            "weight": 0.14285714285714285,
            "weighted_cpu": 47719.16750198946
        },
        {
            "idx": 4,
            "is_source": false,
            "is_sink": false,
            "name": "op_4",
            "cpu": 334034.1725139262,
            "payload": 0.32032588041552085,
            "weight": 0.14285714285714285,
            "weighted_cpu": 47719.16750198946
        },
        {
            "idx": 5,
            "is_source": false,
            "is_sink": false,
            "name": "op_5",
            "cpu": 334034.1725139262,
            "payload": 0.2843485492665033,
            "weight": 0.14285714285714285,
            "weighted_cpu": 47719.16750198946
        },
        {
            "idx": 6,
            "is_source": false,
            "is_sink": false,
            "name": "op_6",
            "cpu": 334034.1725139262,
            "payload": 0.47984429619222063,
            "weight": 0.14285714285714285,
            "weighted_cpu": 47719.16750198946
        },
        {
            "idx": 7,
            "is_source": false,
            "is_sink": false,
            "name": "op_7",
            "cpu": 334034.1725139262,
            "payload": 0.27834437442053317,
            "weight": 0.14285714285714285,
            "weighted_cpu": 47719.16750198946
        },
        {
            "idx": 8,
            "is_source": false,
            "is_sink": false,
            "name": "op_8",
            "cpu": 395965.8274860738,
            "payload": 0.035387984546492335,
            "weight": 0.14285714285714285,
            "weighted_cpu": 56566.54678372482
        },
        {
            "idx": 9,
            "is_source": false,
            "is_sink": false,
            "name": "op_9",
            "cpu": 395965.8274860738,
            "payload": 0.249104801695142,
            "weight": 0.14285714285714285,
            "weighted_cpu": 56566.54678372482
        },
        {
            "idx": 10,
            "is_source": false,
            "is_sink": false,
            "name": "op_10",
            "cpu": 395965.8274860738,
            "payload": 0.2674475943972506,
            "weight": 0.14285714285714285,
            "weighted_cpu": 56566.54678372482
        },
        {
            "idx": 11,
            "is_source": false,
            "is_sink": false,
            "name": "op_11",
            "cpu": 395965.8274860738,
            "payload": 0.13089755542862275,
            "weight": 0.14285714285714285,
            "weighted_cpu": 56566.54678372482
        },
        {
            "idx": 12,
            "is_source": false,
            "is_sink": false,
            "name": "op_12",
            "cpu": 395965.8274860738,
            "payload": 0.27063010580868396,
            "weight": 0.14285714285714285,
            "weighted_cpu": 56566.54678372482
        },
        {
            "idx": 13,
            "is_source": false,
            "is_sink": false,
            "name": "op_13",
            "cpu": 395965.8274860738,
            "payload": 0.29977731152031994,
            "weight": 0.14285714285714285,
            "weighted_cpu": 56566.54678372482
        },
        {
            "idx": 14,
            "is_source": false,
            "is_sink": false,
            "name": "op_14",
            "cpu": 395965.8274860738,
            "payload": 0.1367759502040331,
            "weight": 0.14285714285714285,
            "weighted_cpu": 56566.54678372482
        },
        {
            "idx": 15,
            "is_source": false,
            "is_sink": true,
            "name": "op_15",
            "cpu": 10000.0,
            "payload": 0.0,
            "weight": 1.0,
            "weighted_cpu": 10000.0
        }
    ],
    "connections": [
        {
            "from_vertex": 0,
            "to_vertex": 1,
            "selectivity": 0.14285714285714285,
            "weight": 0.0578481945447772
        },
        {
            "from_vertex": 0,
            "to_vertex": 2,
            "selectivity": 0.14285714285714285,
            "weight": 0.0578481945447772
        },
        {
            "from_vertex": 0,
            "to_vertex": 3,
            "selectivity": 0.14285714285714285,
            "weight": 0.0578481945447772
        },
        {
            "from_vertex": 0,
            "to_vertex": 4,
            "selectivity": 0.14285714285714285,
            "weight": 0.0578481945447772
        },
        {
            "from_vertex": 0,
            "to_vertex": 5,
            "selectivity": 0.14285714285714285,
            "weight": 0.0578481945447772
        },
        {
            "from_vertex": 0,
            "to_vertex": 6,
            "selectivity": 0.14285714285714285,
            "weight": 0.0578481945447772
        },
        {
            "from_vertex": 0,
            "to_vertex": 7,
            "selectivity": 0.14285714285714285,
            "weight": 0.0578481945447772
        },
        {
            "from_vertex": 1,
            "to_vertex": 8,
            "selectivity": 1.0,
            "weight": 0.054276941990193756
        },
        {
            "from_vertex": 2,
            "to_vertex": 9,
            "selectivity": 1.0,
            "weight": 0.0074212086456860085
        },
        {
            "from_vertex": 3,
            "to_vertex": 10,
            "selectivity": 1.0,
            "weight": 0.033063084901479
        },
        {
            "from_vertex": 4,
            "to_vertex": 11,
            "selectivity": 1.0,
            "weight": 0.04576084005936012
        },
        {
            "from_vertex": 5,
            "to_vertex": 12,
            "selectivity": 1.0,
            "weight": 0.040621221323786184
        },
        {
            "from_vertex": 6,
            "to_vertex": 13,
            "selectivity": 1.0,
            "weight": 0.06854918517031723
        },
        {
            "from_vertex": 7,
            "to_vertex": 14,
            "selectivity": 1.0,
            "weight": 0.03976348206007616
        },
        {
            "from_vertex": 8,
            "to_vertex": 15,
            "selectivity": 1.0,
            "weight": 0.005055426363784619
        },
        {
            "from_vertex": 9,
            "to_vertex": 15,
            "selectivity": 1.0,
            "weight": 0.03558640024216314
        },
        {
            "from_vertex": 10,
            "to_vertex": 15,
            "selectivity": 1.0,
            "weight": 0.038206799199607226
        },
        {
            "from_vertex": 11,
            "to_vertex": 15,
            "selectivity": 1.0,
            "weight": 0.018699650775517534
        },
        {
            "from_vertex": 12,
            "to_vertex": 15,
            "selectivity": 1.0,
            "weight": 0.03866144368695485
        },
        {
            "from_vertex": 13,
            "to_vertex": 15,
            "selectivity": 1.0,
            "weight": 0.04282533021718856
        },
        {
            "from_vertex": 14,
            "to_vertex": 15,
            "selectivity": 1.0,
            "weight": 0.019539421457719013
        }
    ],
    "max_throughput": 10000,
    "event_rate": 10000,
    "num_vms": 3
}